livefield/__init__.py
livefield/fields.py
livefield/managers.py
livefield/models.py
livefield/querysets.py
django_livefield-4.1.0.dist-info/AUTHORS.rst
django_livefield-4.1.0.dist-info/LICENSE.txt
django_livefield-4.1.0.dist-info/METADATA
django_livefield-4.1.0.dist-info/WHEEL
django_livefield-4.1.0.dist-info/top_level.txt
django_livefield-4.1.0.dist-info/RECORD
