Metadata-Version: 2.1
Name: django-livefield
Version: 4.1.0
Summary: Convenient soft-deletion support for Django models
Home-page: https://github.com/hearsaycorp/django-livefield
Author: Hearsay Social
Author-email: opensource@hearsaysocial.com
License: MIT
Keywords: python django soft-delete
Classifier: Development Status :: 5 - Production/Stable
Classifier: Framework :: Django :: 3.2
Classifier: Framework :: Django :: 4.0
Classifier: Framework :: Django :: 4.1
Classifier: Framework :: Django :: 4.2
Classifier: Framework :: Django :: 5.0
Classifier: Programming Language :: Python :: 3.8
Classifier: Programming Language :: Python :: 3.9
Classifier: Programming Language :: Python :: 3.10
Classifier: Programming Language :: Python :: 3.11
Classifier: Programming Language :: Python :: 3.12
License-File: LICENSE.txt
License-File: AUTHORS.rst
Requires-Dist: Django <5.1,>=3.2
